img_resizer/__init__.py
img_resizer/main.py
resize_img-0.7.dist-info/LICENSE
resize_img-0.7.dist-info/METADATA
resize_img-0.7.dist-info/WHEEL
resize_img-0.7.dist-info/entry_points.txt
resize_img-0.7.dist-info/top_level.txt
resize_img-0.7.dist-info/RECORD
