Metadata-Version: 2.1
Name: resize_img
Version: 0.7
License-File: LICENSE
Requires-Dist: Pillow
Requires-Dist: setuptools
Requires-Dist: wheel
Requires-Dist: twine
